{
  "url": "https://support.grammarly.com/hc/en-us/articles/115000090772-Report-grammar-checking-error",
  "scraped_at": "2025-08-11T20:36:18.083921+00:00",
  "title": "Report grammar checking error",
  "content": "Grammarly’s suggestion is wrong\nIf Grammarly erroneously highlighted something in your text as a mistake, please\nsubmit a support ticket\nand include the following details:\nSpecify the mistake that was flagged.\nCopy and paste the original sentence or paragraph where the issue occurred.\nThis information will help us investigate this issue further. Thank you for your help in improving our algorithms!\nGrammarly didn’t find a mistake in my text\nThe Grammarly Editor works most effectively when checking naturally written texts. Grammarly is built to find and correct natural errors because the patterns are based on real writing and real errors.\nIf Grammarly didn’t flag a mistake in your text, make sure that all categories of suggestions are enabled (i.e., correctness, clarity, engagement, delivery).\nIf the issue persists, please submit the following information\nin a support ticket\nto help our grammarian staff improve our algorithms:\nSpecify the mistake that wasn’t found.\nCopy and paste the original sentence or paragraph where Grammarly did not pick up the error.\nNote:\nGrammarly Free identifies many basic writing mistakes. Some suggestions are only available in paid Grammarly plans. Paid plans include everything that comes with Grammarly Free version and also flag many additional advanced writing mistakes. You can learn more about our paid plans here:\nGrammarly Plans",
  "category": "Ideas & Feedback",
  "tags": []
}