{
  "url": "https://support.grammarly.com/hc/en-us/articles/360049189071-Can-I-get-a-refund-from-Grammarly",
  "scraped_at": "2025-08-11T20:47:00.911084+00:00",
  "title": "Can I get a refund from Grammarly?",
  "content": "You can cancel your paid Grammarly account at any time. However, as outlined in our\nTerms of Service\n, refunds are issued only if required by law.\nNote:\nIf you purchased your subscription from the App Store,\ncontact Apple\nto request a refund.\nRelated articles\nHow do I cancel my Grammarly subscription?\nHow does Grammarly charge my account?",
  "category": "Manage Payments",
  "tags": []
}